{
    "Statistics": "Статистика",
    "Settings": "Настройки",
    "Mycontributions": "Мои публикации",
    "SubscribeToRSSFeed": "Подписаться на канал RSS",
    "PinToThisTab": "Закрепить на этой вкладке",
    "mediaPluralUp": "Материалы",
    "galleryPluralUp" : "Галерея",
    "mediaUp": "Материалы",
    "media": "материалы",
    "mediaPlural": "материалы",
    "ideasPluralUp": "Идеи",
    "ideasPipeline": "Источник идей",
    "postsPluralUp": "Публикации",
    "ideasUp": "Идея",
    "ideas": "идея",
    "ideasPlural": "идеи",
    "membersPluralUp": "Участники",
    "membersUp": "Участник",
    "surveysPluralUp": "Опросы",
    "surveysUp": "Опрос",
    "members": "участник",
    "membersPlural": "участники",
    "questionsPluralUp": "Вопросы",
    "questionsUp": "Вопрос",
    "questions": "вопрос",
    "questionsPlural": "вопросы",
    "wikiUp": "Вики",
    "Home": "Новые возможности",
    "Subscribe": "Подписаться на новое содержимое",
    "Unsubscribe": "Отменить подписку на новое содержимое",
    "COMMUNITIES": "СООБЩЕСТВА",
    "CONVERSATIONS": "БЕСЕДЫ"
}
