{
    "coachmark_example":        "Exemple de Coachmark",
    "coachmark_player":         "Ouvrir le menu de personnalisation pour compléter l'URL de la vidéo",
    "coachmark_webviewer":      "Ouvrir le menu de personnalisation pour compléter l'URL",
    "coachmark_map_tools":      "Utiliser cette commande pour ajouter des notes autocollantes, des autocollants et des membres d'équipe",
    "coachmark_map_customize":  "Utiliser cette commande pour créer un ou plusieurs tableaux, les personnaliser et ajouter des Leangets",
    "coachmark_map_select":     "Utiliser cette commande pour supprimer une ou plusieurs notes autocollantes",
    "coachmark_board":          "Ouvrir le menu de personnalisation pour configurer ce panneau",
    "coachmark_kpi":            "Ouvrir le menu de personnalisation pour configurer le KPI"
}
