{
    "coachmark_example":        "コーチマークの例",
    "coachmark_player":         "カスタマイズ メニューを開いてビデオ URL を入力します",
    "coachmark_webviewer":      "カスタマイズ メニューを開いて URL を入力します",
    "coachmark_map_tools":      "このコマンドを使用して付箋、ステッカーおよびチーム メンバーを追加します",
    "coachmark_map_customize":  "このコマンドを使用して 1 つ以上のボードを作成、カスタマイズし、Leanget を追加します",
    "coachmark_map_select":     "このコマンドを使用して 1 つ以上の付箋を削除します",
    "coachmark_board":          "カスタマイズ メニューを開いてこのボードを構成します",
    "coachmark_kpi":            "カスタマイズ メニューを開いて KPI を構成します"
}
