{
	"addColor": "Agregar color",
	"back": "Atrás",
	"cancel": "Cancelar",
	"colorError": "Introduzca un color exclusivo con formato hexadecimal de 6 dígitos.",
	"create": "Crear",
	"duplicateNameError": "Ya existe un material con este nombre específico, introduzca un nombre específico único.",
	"genericType": "Familia de materiales",
  "genericTypeError": "Seleccione una familia de materiales.",
	"modelSavedMessage": " se ha guardado.",
	"name": "Nombre específico",
	"nameSearch": "Buscar por nombre específico",
	"nameError": "Introduzca los criterios de búsqueda.",
  "noResults": "No hay ningún resultado.",
  "remove": "Eliminar",
  "save": "Guardar",
  "saveConfirmation": "Confirmación de guardado",
  "saveConfirmationMessage": "¿Seguro que desea guardar el material?",
  "search": "Buscar",
	"searchBy": "Buscar por",
	"searchSelectionError": "Seleccione el tipo de búsqueda.",
	"specificType": "Clase de material",
	"specificTypeError": "Seleccione una clase de material.",
	"specificTypeSearch": "Buscar por clase de material",
  "supportedColors": "Colores compatibles"
}
