{
	"SimulationObject"	: "Physiksimulation",
	"Loading"			: "WIRD GELADEN",

	"Configuring" 		: "WIRD KONFIGUIERT",
	"Starting" 			: "WIRD GESTARTET",
	"Running" 			: "WIRD AUSGEFÜHRT",
	"Paused" 			: "ANGEHALTEN",
	"Queued"			: "IN WARTESCHLANGE GESTELLT",
	"Completed" 		: "ABGESCHLOSSEN",
	"Stopping"			: "WIRD GESTOPPT",
	"Aborted" 			: "ABGEBROCHEN",
	"Failed" 			: "FEHLGESCHLAGEN",
	"SystemFailed" 		: "FEHLGESCHLAGEN",
	"Unknown"			: "UNBEKANNT",

	"Deleting"			: "WIRD GELÖSCHT",

	"WaitingForStation"	: "Warte auf Station",
	"NotStarted"		: "NICHT GESTARTET",

	"JustNow"			: "soeben",
	"SecondsAgo"		: "Sekunden zuvor",
	"AMinuteAgo"		: "Minute zuvor",
	"MinutesAgo"		: "Minuten zuvor",
	"AnHourAgo"			: "eine Stunde zuvor",
	"HoursAgo"			: "Stunden zuvor",
	"ADayAgo"			: "einen Tag zuvor",
	"DaysAgo"			: "Tage zuvor",
	"AMonthAgo"			: "einen Monat zuvor",
	"MonthsAgo"			: "Monate zuvor",
	"AYearAgo"			: "ein Jahr zuvor",
	"YearsAgo"			: "Jahre zuvor",

	"GB"				: "GB",
	"MB"				: "MB",
	"KB"				: "KB"
}
