{
    "MR_Save": "Сохранить",
    "MR_Reset": "Сброс",
    "MR_DefineRule": "Определить таблицу правил",
    "MR_Done": "Готово",
    "MR_Cancel": "Отмена",
    "MR_Basics": "Основы",
    "MR_Name": "Имя",
    "MR_Description": "Описание",
    "MR_Effectivity": "Законченность",
    "MR_Create": "Создать правило матрицы",
    "MR_Mandatory": "Заполнение полей, отмеченных красным курсивом, обязательно",
    "MR_ValidName":"Необходимо ввести допустимое значение для поля \"Имя\"",
    "MR_NON_UNIQUE":"Правило конфигурации (Матрица/Выражение) с таким именем уже существует. Введите другое имя.",
    "MR_ERROR":"Сбой при создании правила",
    "MR_SAVE_ERROR":"Сбой при сохранении правила",
    "MR_SAVE_OK": "Правило матрицы сохранено",
    "MR_SAVE_CONFLICT" : "Правило матрицы содержит по меньшей мере один конфликт",
    "MR_DRIVING_CRITERIA" : "Управляющие критерии",
    "MR_CONSTRAINED_CRITERIA" : "Ограниченные критерии",
    "MR_Settings":"Настройки",
    "MR_displayPic":"Изображения",
    "MR_Availability":"Доступность",
    "MR_Ext_Req":"Внешние требования",
    "MR_local_def":"Локальное определение",
    "MR_defaultValue":"Значение по умолчанию",
    "MR_legend":"Легенда",
    "MR_Req_Comb":"Обязательная комбинация из-за: ",
    "MR_Invalid_Comb":"Недопустимая комбинация из-за: ",
    "MR_UnkReason":"неизвестная причина",
    "MR_Undercomputation":"при вычислении",
    "MR_DescriptionTitle":"Описание",
    "MR_NameTitle":"Название",
    "MR_Default" : "По умолчанию",
    "MR_Available" : "Доступно",
    "MR_NonAvailable" : "Недоступно",
    "MR_Standard" : "Стандартное",
    "MR_InternalSolve" : "Проверка согласованности",
    "Too_Many_Columns" : "Создано слишком много столбцов. Операция перетаскивания отменена",
    "NotAllowForMultiple" : "нельзя использовать в управляющих критериях",
    "MR_CheckInternalConflicts" : "Проверка внутренних конфликтов",
	"MR_SwitchView": "Переключить вид",
	"MR_InconsistentRuleDefinition":"Определение правила в модели не согласовано и не может быть разрешено, поэтому функция поддержки правил отключена",
	"MR_Implied_Rules":"Примененные правила",
	"MR_Set_Columns":"Задать для столбцов значение",
	"MR_Set_Rows" : "Задать для строк значение",
	"MR_Set_Column":"Задать для столбца значение",
	"MR_Set_Row" : "Задать для строки значение",
	"MR_SET_MATRIX" : "Задать для всех критериев значение",
	"MR_Alert_InvalidChars" : "Следующие символы являются недопустимыми\n"
}
