{
  "Nb_New" : "{nbNew} nouvel objet",
  "RenameFile_cmd" : "Renommer le fichier",
  "Include_cmd" : "Inclure dans la portée de sauvegarde",
  "Exclude_cmd":"Exclure de la portée de sauvegarde",
  "Revise_cmd":"Enregistrer comme nouvelle révision",
  "Do_cmd":"Sorties dérivées...",
  "SaveAsNew_cmd":"Enregistrer comme nouveau",
  "Duplicate_cmd":"Enregistrer comme double",
  "Reserve_cmd":"Réserver",
  "Unreserve_cmd":"Annuler la réservation",
  "Filter_cmd":"Fichier non modifié",
  "Bookmark_cmd":"Ajouter au signet",
  "Info_cmd":"Afficher le panneau droit"
}
