<MSVariable>
	<InitialConditionVariables>
		<variables>
			<input>
				<variable>heat_flux</variable>
			</input>
			<output>
				<variable>temperature</variable>
			</output>
		</variables>
	</InitialConditionVariables>
	<CouplingStepVariables>
		<variables>
			<input>
				<variable>heat_flux</variable>
			</input>
			<output>
				<variable>temperature</variable>
			</output>
		</variables>
	</CouplingStepVariables>
	<SpecVariables>
		<variables>
			<input>
				<variable>heat_flux</variable>
			</input>
			<output>
				<variable>temperature</variable>
			</output>
		</variables>
	</SpecVariables>
</MSVariable>
