{
	"Input": "Select Input Files to Include",
	"BatchInput": "Select Batch Files to Include",
	"Execution": "Select Compute Environment",
	"Output": "Select Files to Save",
	"Options": "Set Options",
	"Content": "Content",
	"SystemLog": "Station Log",
	"Properties": "Properties",
	"cloneJob": "Run Again...",
	"previewResults": "Preview Results",
	"deleteJob": "Delete Job...",
	"abortJob": "Abort Job",
	"viewDetails": "View Details",
	"Initializing": "Initializing",
	"Saving": "Saving",
	"Running": "Executing"
}
