{
  "_my_mvs": "Mis versiones de modelo",
  "_recent_mvs": "Abiertas recientemente",
  "_open": "Abrir",
  "_information": "Información",
  "_delete": "Eliminar",
  "_create": "Crear",
  "_no_recent_items": "No hay elementos recientes",
  "_myModelVersions": "Versiones de modelo (filtro: mis)",
  "_myModelVersion": "Versión de modelo (filtro: mi)",

  "_multi_object_not_supported" : "No es posible soltar varios objetos",
  "_type_not_supported" : "tipo no compatible",
  "_no_drag_data" : "No se han recibido datos en el objeto arrastrado",
  "_opening" : "Abriendo",
  "_object_with" : "Objeto con",
  "_service_failure" : "Error del servicio"

}
