{
	"Theanswerwasvotedsuccessfully":"La respuesta se ha votado correctamente.",
	"Yourvotehasbeensuccessfullysaved":"Su voto se ha guardado correctamente.",
	"TheanswercouldnotbevotedPleasetryagain":"No se ha podido votar la respuesta. Vuelva a intentarlo.",
    "YourvotecouldnotbesavedPleasetryagain":"No se ha podido guardar el voto. Inténtelo de nuevo.",
	"Theanswerwasvalidatedsuccessfully":"La respuesta se ha validado correctamente.",
	"TheanswercouldnotbevalidatedPleasetryagain":"No se ha podido validar la respuesta. Inténtelo de nuevo",
	"TheAnswerYouAreLookingForCouldNotBeFoundItMayHaveBeenRemoved": "No se ha podido encontrar la respuesta que busca. Es posible que se haya eliminado.",
	"Vote": "Votar",
	"Unvote": "Anular voto",
	"ValidateAnswer": "Validar respuesta",
	"Comment" : "Comentario"
}
